etudier/__init__.py
etudier/network.html
etudier-0.2.1.dist-info/METADATA
etudier-0.2.1.dist-info/WHEEL
etudier-0.2.1.dist-info/entry_points.txt
etudier-0.2.1.dist-info/RECORD
