Metadata-Version: 2.3
Name: etudier
Version: 0.2.1
Summary: Collect a citation graph from Google Scholar
Author-email: Ed Summers <ehs@pobox.com>
Requires-Python: >=3.8
Requires-Dist: lxml-html-clean>=0.3.1
Requires-Dist: networkx>=2.8
Requires-Dist: requests-html>=0.10
Requires-Dist: requests>=2.28
Requires-Dist: selenium>=4.7
